[
    {
        "6ukvMSg9": "1", 
        "8f7mxN3j": "0", 
        "gak9Gb3N": "20"
    }, 
    {
        "6ukvMSg9": "2", 
        "8f7mxN3j": "100", 
        "gak9Gb3N": "20"
    }, 
    {
        "6ukvMSg9": "3", 
        "8f7mxN3j": "200", 
        "gak9Gb3N": "20"
    }, 
    {
        "6ukvMSg9": "4", 
        "8f7mxN3j": "300", 
        "gak9Gb3N": "20"
    }, 
    {
        "6ukvMSg9": "1", 
        "8f7mxN3j": "0", 
        "gak9Gb3N": "21"
    }, 
    {
        "6ukvMSg9": "2", 
        "8f7mxN3j": "100", 
        "gak9Gb3N": "21"
    }, 
    {
        "6ukvMSg9": "3", 
        "8f7mxN3j": "200", 
        "gak9Gb3N": "21"
    }, 
    {
        "6ukvMSg9": "4", 
        "8f7mxN3j": "300", 
        "gak9Gb3N": "21"
    }, 
    {
        "6ukvMSg9": "1", 
        "8f7mxN3j": "0", 
        "gak9Gb3N": "22"
    }, 
    {
        "6ukvMSg9": "2", 
        "8f7mxN3j": "100", 
        "gak9Gb3N": "22"
    }, 
    {
        "6ukvMSg9": "3", 
        "8f7mxN3j": "200", 
        "gak9Gb3N": "22"
    }, 
    {
        "6ukvMSg9": "4", 
        "8f7mxN3j": "300", 
        "gak9Gb3N": "22"
    }
]