[
    {
        "3HriTp6B": "100000315", 
        "VjJQ51uG": "2017-01-01 00:00:00", 
        "e4mG8jTc": "10", 
        "m8ivD4NX": "2030-12-31 23:59:59"
    }, 
    {
        "3HriTp6B": "100005805", 
        "VjJQ51uG": "2017-01-01 00:00:00", 
        "e4mG8jTc": "10", 
        "m8ivD4NX": "2030-12-31 23:59:59"
    }, 
    {
        "3HriTp6B": "100005905", 
        "VjJQ51uG": "2018-10-19 08:00:00", 
        "e4mG8jTc": "10", 
        "m8ivD4NX": "2030-12-31 23:59:59"
    }, 
    {
        "3HriTp6B": "100006105", 
        "VjJQ51uG": "2017-01-01 00:00:00", 
        "e4mG8jTc": "10", 
        "m8ivD4NX": "2030-12-31 23:59:59"
    }, 
    {
        "3HriTp6B": "100006805", 
        "VjJQ51uG": "2018-11-26 08:00:00", 
        "e4mG8jTc": "10", 
        "m8ivD4NX": "2030-12-31 23:59:59"
    }, 
    {
        "3HriTp6B": "100007205", 
        "VjJQ51uG": "2017-01-01 00:00:00", 
        "e4mG8jTc": "10", 
        "m8ivD4NX": "2030-12-31 23:59:59"
    }, 
    {
        "3HriTp6B": "100007505", 
        "VjJQ51uG": "2018-11-26 08:00:00", 
        "e4mG8jTc": "10", 
        "m8ivD4NX": "2030-12-31 23:59:59"
    }, 
    {
        "3HriTp6B": "100007705", 
        "VjJQ51uG": "2018-10-22 08:00:00", 
        "e4mG8jTc": "10", 
        "m8ivD4NX": "2030-12-31 23:59:59"
    }, 
    {
        "3HriTp6B": "100008005", 
        "VjJQ51uG": "2018-10-19 08:00:00", 
        "e4mG8jTc": "10", 
        "m8ivD4NX": "2030-12-31 23:59:59"
    }, 
    {
        "3HriTp6B": "100008205", 
        "VjJQ51uG": "2018-10-22 08:00:00", 
        "e4mG8jTc": "10", 
        "m8ivD4NX": "2030-12-31 23:59:59"
    }, 
    {
        "3HriTp6B": "100008605", 
        "VjJQ51uG": "2018-09-28 08:00:00", 
        "e4mG8jTc": "10", 
        "m8ivD4NX": "2030-12-31 23:59:59"
    }, 
    {
        "3HriTp6B": "100009105", 
        "VjJQ51uG": "2018-11-26 08:00:00", 
        "e4mG8jTc": "10", 
        "m8ivD4NX": "2030-12-31 23:59:59"
    }, 
    {
        "3HriTp6B": "100009805", 
        "VjJQ51uG": "2018-11-23 08:00:00", 
        "e4mG8jTc": "10", 
        "m8ivD4NX": "2030-12-31 23:59:59"
    }, 
    {
        "3HriTp6B": "100010405", 
        "VjJQ51uG": "2018-11-23 08:00:00", 
        "e4mG8jTc": "10", 
        "m8ivD4NX": "2030-12-31 23:59:59"
    }, 
    {
        "3HriTp6B": "100011705", 
        "VjJQ51uG": "2018-11-26 08:00:00", 
        "e4mG8jTc": "10", 
        "m8ivD4NX": "2030-12-31 23:59:59"
    }, 
    {
        "3HriTp6B": "100012405", 
        "VjJQ51uG": "2018-11-23 08:00:00", 
        "e4mG8jTc": "10", 
        "m8ivD4NX": "2030-12-31 23:59:59"
    }, 
    {
        "3HriTp6B": "100015405", 
        "VjJQ51uG": "2017-01-01 00:00:00", 
        "e4mG8jTc": "10", 
        "m8ivD4NX": "2030-12-31 23:59:59"
    }, 
    {
        "3HriTp6B": "100015805", 
        "VjJQ51uG": "2018-09-28 08:00:00", 
        "e4mG8jTc": "10", 
        "m8ivD4NX": "2030-12-31 23:59:59"
    }, 
    {
        "3HriTp6B": "100016205", 
        "VjJQ51uG": "2018-09-28 08:00:00", 
        "e4mG8jTc": "10", 
        "m8ivD4NX": "2030-12-31 23:59:59"
    }, 
    {
        "3HriTp6B": "100016905", 
        "VjJQ51uG": "2018-10-26 08:00:00", 
        "e4mG8jTc": "10", 
        "m8ivD4NX": "2030-12-31 23:59:59"
    }, 
    {
        "3HriTp6B": "100017105", 
        "VjJQ51uG": "2018-11-23 08:00:00", 
        "e4mG8jTc": "10", 
        "m8ivD4NX": "2030-12-31 23:59:59"
    }, 
    {
        "3HriTp6B": "202000505", 
        "VjJQ51uG": "2018-09-28 08:00:00", 
        "e4mG8jTc": "10", 
        "m8ivD4NX": "2030-12-31 23:59:59"
    }, 
    {
        "3HriTp6B": "203000105", 
        "VjJQ51uG": "2018-10-01 08:00:00", 
        "e4mG8jTc": "10", 
        "m8ivD4NX": "2030-12-31 23:59:59"
    }, 
    {
        "3HriTp6B": "203000205", 
        "VjJQ51uG": "2017-01-01 00:00:00", 
        "e4mG8jTc": "10", 
        "m8ivD4NX": "2030-12-31 23:59:59"
    }, 
    {
        "3HriTp6B": "204000115", 
        "VjJQ51uG": "2017-01-01 00:00:00", 
        "e4mG8jTc": "10", 
        "m8ivD4NX": "2030-12-31 23:59:59"
    }, 
    {
        "3HriTp6B": "205000805", 
        "VjJQ51uG": "2017-01-01 00:00:00", 
        "e4mG8jTc": "10", 
        "m8ivD4NX": "2030-12-31 23:59:59"
    }, 
    {
        "3HriTp6B": "206000125", 
        "VjJQ51uG": "2018-10-01 08:00:00", 
        "e4mG8jTc": "10", 
        "m8ivD4NX": "2030-12-31 23:59:59"
    }, 
    {
        "3HriTp6B": "208000105", 
        "VjJQ51uG": "2017-01-01 00:00:00", 
        "e4mG8jTc": "10", 
        "m8ivD4NX": "2030-12-31 23:59:59"
    }, 
    {
        "3HriTp6B": "208000205", 
        "VjJQ51uG": "2017-01-01 00:00:00", 
        "e4mG8jTc": "10", 
        "m8ivD4NX": "2030-12-31 23:59:59"
    }, 
    {
        "3HriTp6B": "209000705", 
        "VjJQ51uG": "2018-10-22 08:00:00", 
        "e4mG8jTc": "10", 
        "m8ivD4NX": "2030-12-31 23:59:59"
    }, 
    {
        "3HriTp6B": "209001105", 
        "VjJQ51uG": "2018-10-22 08:00:00", 
        "e4mG8jTc": "10", 
        "m8ivD4NX": "2030-12-31 23:59:59"
    }, 
    {
        "3HriTp6B": "210000105", 
        "VjJQ51uG": "2018-09-28 08:00:00", 
        "e4mG8jTc": "10", 
        "m8ivD4NX": "2030-12-31 23:59:59"
    }, 
    {
        "3HriTp6B": "211000405", 
        "VjJQ51uG": "2018-10-19 08:00:00", 
        "e4mG8jTc": "10", 
        "m8ivD4NX": "2030-12-31 23:59:59"
    }, 
    {
        "3HriTp6B": "211000805", 
        "VjJQ51uG": "2018-09-14 08:00:00", 
        "e4mG8jTc": "10", 
        "m8ivD4NX": "2030-12-31 23:59:59"
    }, 
    {
        "3HriTp6B": "211000905", 
        "VjJQ51uG": "2018-09-14 08:00:00", 
        "e4mG8jTc": "10", 
        "m8ivD4NX": "2030-12-31 23:59:59"
    }, 
    {
        "3HriTp6B": "212000505", 
        "VjJQ51uG": "2018-11-23 08:00:00", 
        "e4mG8jTc": "10", 
        "m8ivD4NX": "2030-12-31 23:59:59"
    }, 
    {
        "3HriTp6B": "213000105", 
        "VjJQ51uG": "2017-01-01 00:00:00", 
        "e4mG8jTc": "10", 
        "m8ivD4NX": "2030-12-31 23:59:59"
    }, 
    {
        "3HriTp6B": "215000105", 
        "VjJQ51uG": "2018-11-26 08:00:00", 
        "e4mG8jTc": "10", 
        "m8ivD4NX": "2030-12-31 23:59:59"
    }, 
    {
        "3HriTp6B": "215000205", 
        "VjJQ51uG": "2018-11-26 08:00:00", 
        "e4mG8jTc": "10", 
        "m8ivD4NX": "2030-12-31 23:59:59"
    }, 
    {
        "3HriTp6B": "215000505", 
        "VjJQ51uG": "2018-10-19 08:00:00", 
        "e4mG8jTc": "10", 
        "m8ivD4NX": "2030-12-31 23:59:59"
    }, 
    {
        "3HriTp6B": "215001105", 
        "VjJQ51uG": "2018-10-01 08:00:00", 
        "e4mG8jTc": "10", 
        "m8ivD4NX": "2030-12-31 23:59:59"
    }, 
    {
        "3HriTp6B": "253000105", 
        "VjJQ51uG": "2017-01-01 00:00:00", 
        "e4mG8jTc": "10", 
        "m8ivD4NX": "2030-12-31 23:59:59"
    }, 
    {
        "3HriTp6B": "253000115", 
        "VjJQ51uG": "2018-09-28 08:00:00", 
        "e4mG8jTc": "10", 
        "m8ivD4NX": "2030-12-31 23:59:59"
    }, 
    {
        "3HriTp6B": "253000205", 
        "VjJQ51uG": "2017-01-01 00:00:00", 
        "e4mG8jTc": "10", 
        "m8ivD4NX": "2030-12-31 23:59:59"
    }, 
    {
        "3HriTp6B": "253000215", 
        "VjJQ51uG": "2018-10-01 08:00:00", 
        "e4mG8jTc": "10", 
        "m8ivD4NX": "2030-12-31 23:59:59"
    }, 
    {
        "3HriTp6B": "253000805", 
        "VjJQ51uG": "2017-01-01 00:00:00", 
        "e4mG8jTc": "10", 
        "m8ivD4NX": "2030-12-31 23:59:59"
    }, 
    {
        "3HriTp6B": "254000105", 
        "VjJQ51uG": "2018-10-01 08:00:00", 
        "e4mG8jTc": "10", 
        "m8ivD4NX": "2030-12-31 23:59:59"
    }, 
    {
        "3HriTp6B": "254000205", 
        "VjJQ51uG": "2018-10-01 08:00:00", 
        "e4mG8jTc": "10", 
        "m8ivD4NX": "2030-12-31 23:59:59"
    }, 
    {
        "3HriTp6B": "254000905", 
        "VjJQ51uG": "2018-10-19 08:00:00", 
        "e4mG8jTc": "10", 
        "m8ivD4NX": "2030-12-31 23:59:59"
    }, 
    {
        "3HriTp6B": "254001805", 
        "VjJQ51uG": "2018-11-16 08:00:00", 
        "e4mG8jTc": "10", 
        "m8ivD4NX": "2030-12-31 23:59:59"
    }, 
    {
        "3HriTp6B": "254001905", 
        "VjJQ51uG": "2018-11-16 08:00:00", 
        "e4mG8jTc": "10", 
        "m8ivD4NX": "2030-12-31 23:59:59"
    }, 
    {
        "3HriTp6B": "302001305", 
        "VjJQ51uG": "2017-01-01 00:00:00", 
        "e4mG8jTc": "10", 
        "m8ivD4NX": "2030-12-31 23:59:59"
    }, 
    {
        "3HriTp6B": "302001405", 
        "VjJQ51uG": "2018-11-23 08:00:00", 
        "e4mG8jTc": "10", 
        "m8ivD4NX": "2030-12-31 23:59:59"
    }, 
    {
        "3HriTp6B": "401001105", 
        "VjJQ51uG": "2018-10-22 08:00:00", 
        "e4mG8jTc": "10", 
        "m8ivD4NX": "2030-12-31 23:59:59"
    }, 
    {
        "3HriTp6B": "401001405", 
        "VjJQ51uG": "2018-10-19 08:00:00", 
        "e4mG8jTc": "10", 
        "m8ivD4NX": "2030-12-31 23:59:59"
    }, 
    {
        "3HriTp6B": "401001705", 
        "VjJQ51uG": "2018-09-28 08:00:00", 
        "e4mG8jTc": "10", 
        "m8ivD4NX": "2030-12-31 23:59:59"
    }, 
    {
        "3HriTp6B": "401004405", 
        "VjJQ51uG": "2018-10-12 08:00:00", 
        "e4mG8jTc": "10", 
        "m8ivD4NX": "2030-12-31 23:59:59"
    }, 
    {
        "3HriTp6B": "401004605", 
        "VjJQ51uG": "2018-10-12 08:00:00", 
        "e4mG8jTc": "10", 
        "m8ivD4NX": "2030-12-31 23:59:59"
    }, 
    {
        "3HriTp6B": "401005305", 
        "VjJQ51uG": "2018-10-05 08:00:00", 
        "e4mG8jTc": "10", 
        "m8ivD4NX": "2030-12-31 23:59:59"
    }, 
    {
        "3HriTp6B": "401005405", 
        "VjJQ51uG": "2018-10-05 08:00:00", 
        "e4mG8jTc": "10", 
        "m8ivD4NX": "2030-12-31 23:59:59"
    }
]